speech_metrics/__init__.py
speech_metrics/asteroid_metric.py
speech_metrics/common.py
speech_metrics/der.py
speech_metrics/rttm.py
speech_metrics/signal.py
speech_metrics/slot_filling.py
speech_metrics/translation.py
speech_metrics/dscorelib/__init__.py
speech_metrics/dscorelib/argparse.py
speech_metrics/dscorelib/metrics.py
speech_metrics/dscorelib/rttm.py
speech_metrics/dscorelib/score.py
speech_metrics/dscorelib/six.py
speech_metrics/dscorelib/turn.py
speech_metrics/dscorelib/uem.py
speech_metrics/dscorelib/utils.py
speech_metrics/dscorelib/tests/__init__.py
speech_metrics/dscorelib/tests/test_metrics.py
speech_metrics/dscorelib/tests/test_score.py
speech_metrics/dscorelib/tests/test_turn.py
speech_metrics/dscorelib/tests/test_uem.py
speech_metrics-0.2.2.dist-info/LICENSE
speech_metrics-0.2.2.dist-info/METADATA
speech_metrics-0.2.2.dist-info/WHEEL
speech_metrics-0.2.2.dist-info/top_level.txt
speech_metrics-0.2.2.dist-info/RECORD
