Metadata-Version: 2.1
Name: speech_metrics
Version: 0.2.2
Summary: A lightweight package for common metrics in speech processing
Home-page: https://github.com/leo19941227/speech_metrics
Author: Shu-wen Yang
Author-email: leo19941227@gmail.com
License: MIT License
Classifier: Programming Language :: Python :: 3
Classifier: License :: OSI Approved :: MIT License
Classifier: Operating System :: OS Independent
License-File: LICENSE
Requires-Dist: editdistance
Requires-Dist: pb-bss-eval
Requires-Dist: sacrebleu
